{
    "codeToName": {
        "32": "space",
        "33": "exclam",
        "34": "quotedbl",
        "35": "numbersign",
        "36": "dollar",
        "37": "percent",
        "38": "ampersand",
        "39": "quotesingle",
        "40": "parenleft",
        "41": "parenright",
        "42": "asterisk",
        "43": "plus",
        "44": "comma",
        "45": "hyphen",
        "46": "period",
        "47": "slash",
        "48": "zero",
        "49": "one",
        "50": "two",
        "51": "three",
        "52": "four",
        "53": "five",
        "54": "six",
        "55": "seven",
        "56": "eight",
        "57": "nine",
        "58": "colon",
        "59": "semicolon",
        "60": "less",
        "61": "equal",
        "62": "greater",
        "63": "question",
        "64": "at",
        "91": "bracketleft",
        "92": "backslash",
        "93": "bracketright",
        "94": "asciicircum",
        "95": "underscore",
        "96": "grave",
        "123": "braceleft",
        "124": "bar",
        "125": "braceright",
        "126": "asciitilde",
        "162": "cent",
        "178": "uni00B2",
        "179": "uni00B3",
        "185": "uni00B9",
        "215": "multiply",
        "247": "divide",
        "700": "afii57929",
        "784": "uni0310",
        "2404": "uni0964",
        "2405": "uni0965",
        "2946": "anusvarataml",
        "2947": "visargataml",
        "2949": "ataml",
        "2950": "aataml",
        "2951": "itaml",
        "2952": "iitaml",
        "2953": "utaml",
        "2954": "uutaml",
        "2958": "etaml",
        "2959": "eetaml",
        "2960": "aitaml",
        "2962": "otaml",
        "2963": "ootaml",
        "2964": "autaml",
        "2965": "kataml",
        "2969": "ngataml",
        "2970": "cataml",
        "2972": "jataml",
        "2974": "nyataml",
        "2975": "ttataml",
        "2979": "nnataml",
        "2980": "tataml",
        "2984": "nataml",
        "2985": "nnnataml",
        "2986": "pataml",
        "2990": "mataml",
        "2991": "yataml",
        "2992": "rataml",
        "2993": "rrataml",
        "2994": "lataml",
        "2995": "llataml",
        "2996": "lllataml",
        "2997": "vataml",
        "2998": "shataml",
        "2999": "ssataml",
        "3000": "sataml",
        "3001": "hataml",
        "3006": "aasigntaml",
        "3007": "isigntaml",
        "3008": "iisigntaml",
        "3009": "usigntaml",
        "3010": "uusigntaml",
        "3014": "esigntaml",
        "3015": "eesigntaml",
        "3016": "aisigntaml",
        "3018": "osigntaml",
        "3019": "oosigntaml",
        "3020": "ausigntaml",
        "3021": "viramataml",
        "3024": "omtaml",
        "3031": "aulengthtaml",
        "3046": "zerotaml",
        "3047": "onetaml",
        "3048": "twotaml",
        "3049": "threetaml",
        "3050": "fourtaml",
        "3051": "fivetaml",
        "3052": "sixtaml",
        "3053": "seventaml",
        "3054": "eighttaml",
        "3055": "ninetaml",
        "3056": "tentaml",
        "3057": "onehundredtaml",
        "3058": "onethousandtaml",
        "3059": "daysigntaml",
        "3060": "monthsigntaml",
        "3061": "yearsigntaml",
        "3062": "debitsigntaml",
        "3063": "creditsigntaml",
        "3064": "asabovesigntaml",
        "3065": "rupeesigntaml",
        "3066": "numbersigntaml",
        "8204": "zerowidthnonjoiner",
        "8205": "zerowidthjoiner",
        "8211": "endash",
        "8212": "emdash",
        "8216": "quoteleft",
        "8217": "quoteright",
        "8220": "quotedblleft",
        "8221": "quotedblright",
        "8230": "ellipsis",
        "8308": "uni2074",
        "8321": "uni2081",
        "8322": "uni2082",
        "8323": "uni2083",
        "8324": "uni2084",
        "8377": "inr_currency",
        "8722": "minus",
        "9676": "quotedcircle",
        "61440": "uniF000"
    },
    "isUnicode": true,
    "EncodingScheme": "FontSpecific",
    "FontName": "Lohit Tamil",
    "FullName": "Lohit Tamil",
    "Version": "2.91.1",
    "PostScriptName": "Lohit-Tamil",
    "Weight": "Medium",
    "ItalicAngle": "0",
    "IsFixedPitch": "false",
    "UnderlineThickness": "23",
    "UnderlinePosition": "-348",
    "FontHeightOffset": "0",
    "Ascender": "850",
    "Descender": "-364",
    "FontBBox": [
        "-439",
        "-348",
        "1726",
        "845"
    ],
    "StartCharMetrics": "255",
    "C": {
        "32": 300,
        "33": 275,
        "34": 407,
        "35": 944,
        "36": 556,
        "37": 780,
        "38": 783,
        "39": 258,
        "40": 420,
        "41": 420,
        "42": 546,
        "43": 600,
        "44": 275,
        "45": 479,
        "46": 275,
        "47": 479,
        "48": 600,
        "49": 600,
        "50": 600,
        "51": 600,
        "52": 600,
        "53": 600,
        "54": 600,
        "55": 599,
        "56": 600,
        "57": 600,
        "58": 275,
        "59": 275,
        "60": 661,
        "61": 479,
        "62": 661,
        "63": 600,
        "64": 1011,
        "91": 474,
        "92": 713,
        "93": 474,
        "94": 563,
        "95": 747,
        "96": 367,
        "123": 540,
        "124": 252,
        "125": 540,
        "126": 773,
        "162": 542,
        "178": 341,
        "179": 349,
        "185": 302,
        "215": 520,
        "247": 576,
        "700": 258,
        "784": 1000,
        "2404": 330,
        "2405": 521,
        "2946": 0,
        "2947": 784,
        "2949": 1111,
        "2950": 1265,
        "2951": 973,
        "2952": 705,
        "2953": 907,
        "2954": 1259,
        "2958": 780,
        "2959": 778,
        "2960": 803,
        "2962": 838,
        "2963": 839,
        "2964": 1705,
        "2965": 640,
        "2969": 876,
        "2970": 554,
        "2972": 834,
        "2974": 1074,
        "2975": 796,
        "2979": 1272,
        "2980": 651,
        "2984": 642,
        "2985": 970,
        "2986": 744,
        "2990": 805,
        "2991": 857,
        "2992": 517,
        "2993": 681,
        "2994": 830,
        "2995": 902,
        "2996": 805,
        "2997": 957,
        "2998": 1026,
        "2999": 1119,
        "3000": 1074,
        "3001": 1226,
        "3006": 522,
        "3007": 647,
        "3008": 540,
        "3009": 520,
        "3010": 758,
        "3014": 778,
        "3015": 710,
        "3016": 946,
        "3018": 1254,
        "3019": 1190,
        "3020": 1638,
        "3021": 122,
        "3024": 999,
        "3031": 902,
        "3046": 621,
        "3047": 684,
        "3048": 708,
        "3049": 762,
        "3050": 729,
        "3051": 1030,
        "3052": 919,
        "3053": 783,
        "3054": 1115,
        "3055": 964,
        "3056": 804,
        "3057": 668,
        "3058": 741,
        "3059": 889,
        "3060": 1037,
        "3061": 1758,
        "3062": 772,
        "3063": 1305,
        "3064": 1558,
        "3065": 1550,
        "3066": 1168,
        "8204": 12,
        "8205": 17,
        "8211": 540,
        "8212": 1200,
        "8216": 281,
        "8217": 275,
        "8220": 443,
        "8221": 426,
        "8230": 951,
        "8308": 349,
        "8321": 302,
        "8322": 341,
        "8323": 349,
        "8324": 349,
        "8377": 609,
        "8722": 479,
        "9676": 763,
        "61440": 359
    },
    "CIDtoGID_Compressed": true,
    "CIDtoGID": "eJzt0IVuHEEQBcAnhZmZmZmZmZmZmZmZ6Y9zsVaREyt05\/jkpEranZketfrtJhVqkqZpluZpkZZpldZpk7Zpl\/bpkI7plM7pkq7plu7pkZ7pld7pk77pl\/4ZkIEZlMEZUtbUoRmW4RmRkRlVVv\/ojMnYjCurt67xv7ifkIm1TpMqmDS5gt4vplTYD9SHqdUO8JumVTsAAADAd6ZnRrUjAI3QzMwqvWdnTuZmXuZnQVFfmEVZXFqXZGmWZXlRXZGVpfeq0rM6a4ra2qwrduuzIRuL\/aZszpZszbZsz47szK7szp7s\/Tp3X\/bnQA7mUHE+nCM5WlqP5XhO5GRN7dQ3SU\/\/9DvO5GzO5Xwu5GIu5XKu5Gqu5Xpu5GZu5Xbu5G7u5X4e\/NnvAQAAAAAAAAAAABqJh3lU6\/Q4T4rd0zyrWZ\/nRZ2el38\/Vtle\/fDmdd7kbd41WJL3DTYJ6sOHagcAgP\/Ex2oHAAAAAAAAAAAAAAAAAAAAAAAAAAAAAAAAAAAAAAAAAAAAAAAAAAAAAAAAAAAAAAAAAAAAAAAAAAAAAAAAAAAAAAAAAAAAAAAAAAAAAAAAAAAAAAAAAAAAAAAAAAAAAAAAAAAAAPhHfKp2AAAAAAAAAACgUp8BuAwpVw==",
    "_version_": 6
}